odoo/addons/pos_margin/README.rst
odoo/addons/pos_margin/__init__.py
odoo/addons/pos_margin/__manifest__.py
odoo/addons/pos_margin/i18n/es.po
odoo/addons/pos_margin/i18n/it.po
odoo/addons/pos_margin/i18n/pos_margin.pot
odoo/addons/pos_margin/models/__init__.py
odoo/addons/pos_margin/models/pos_config.py
odoo/addons/pos_margin/models/res_config_settings.py
odoo/addons/pos_margin/readme/CONFIGURE.md
odoo/addons/pos_margin/readme/CONTRIBUTORS.md
odoo/addons/pos_margin/readme/DESCRIPTION.md
odoo/addons/pos_margin/readme/HISTORY.md
odoo/addons/pos_margin/readme/ROADMAP.md
odoo/addons/pos_margin/readme/USAGE.md
odoo/addons/pos_margin/report/__init__.py
odoo/addons/pos_margin/report/pos_order_report.py
odoo/addons/pos_margin/static/description/icon.png
odoo/addons/pos_margin/static/description/index.html
odoo/addons/pos_margin/static/description/pos_config_form.png
odoo/addons/pos_margin/static/description/pos_config_setting.png
odoo/addons/pos_margin/static/description/pos_front_end.png
odoo/addons/pos_margin/static/description/pos_order_form.png
odoo/addons/pos_margin/static/src/css/pos_margin.css
odoo/addons/pos_margin/static/src/js/OrderSummaryMargin.esm.js
odoo/addons/pos_margin/static/src/js/models.esm.js
odoo/addons/pos_margin/static/src/xml/pos_margin.xml
odoo/addons/pos_margin/views/res_config_settings_view.xml
odoo/addons/pos_margin/views/view_pos_order.xml
odoo_addon_pos_margin-17.0.1.0.0.2.dist-info/METADATA
odoo_addon_pos_margin-17.0.1.0.0.2.dist-info/WHEEL
odoo_addon_pos_margin-17.0.1.0.0.2.dist-info/top_level.txt
odoo_addon_pos_margin-17.0.1.0.0.2.dist-info/RECORD
